ODConvert/__init__.py
ODConvert/__main__.py
ODConvert/router.py
ODConvert/commands/__init__.py
ODConvert/commands/convert.py
ODConvert/commands/inspect.py
ODConvert/converters/__init__.py
ODConvert/converters/base.py
ODConvert/converters/yolo.py
ODConvert/core/__init__.py
ODConvert/core/autodetect.py
ODConvert/core/boundingbox.py
ODConvert/core/dataset.py
ODConvert/handlers/__init__.py
ODConvert/handlers/coco.py
ODConvert/handlers/yolo.py
ODConvert/handlers/base/__init__.py
ODConvert/handlers/base/handler.py
ODConvert/handlers/base/partition.py
ODConvert/handlers/yolo/partition.py
ODConvert/utils/detect_type.py
ODConvert/utils/paths.py
odconvert-0.0.3.dist-info/licenses/LICENSE.txt
odconvert-0.0.3.dist-info/METADATA
odconvert-0.0.3.dist-info/WHEEL
odconvert-0.0.3.dist-info/entry_points.txt
odconvert-0.0.3.dist-info/top_level.txt
odconvert-0.0.3.dist-info/RECORD
